cod.v
module cod(in,y);
    input [3:0] in;
    output reg [6:0] y;
    always @(in) begin
        case(in)
        4'b0000: y=7'b1111110;  // 0
        4'b0001: y=7'b0110000;  // 1
        4'b0010: y=7'b0101101;  // 2
        4'b0011: y=7'b1111001;  // 3
        4'b0100: y=7'b0110011;  // 4
        4'b0101: y=7'b1011011;  // 5
        4'b0110: y=7'b1011111;  // 6
        4'b0111: y=7'b1110000;  // 7
        4'b1000: y=7'b1111111;  // 8
        4'b1001: y=7'b1111011;  // 9
        4'b1010: y=7'b1110111;  // A
        4'b1011: y=7'b0011111;  // B
        4'b1100: y=7'b1001110;  // C
        4'b1101: y=7'b0111101;  // D
        4'b1110: y=7'b1001111;  // E
        4'b1111: y=7'b1000111;  // F
        endcase
    end
endmodule

cod_tb.v
`timescale 1ns/1ns
`include "cod.v"

module cod_tb;
	reg [3:0] in;
	wire [6:0] y;

	cod uut(in, y);

	initial begin
        $dumpfile("cod_tb.vcd");
        $dumpvars(0, cod_tb);

        in = 4'b0000; // Initialize to 0
        #10; // Wait for 10 time units
        in = 4'b0001; // Set to 1
        #10; // Wait
        in = 4'b0010; // Set to 2
        #10; // Wait
        in = 4'b0011; // Set to 3
        #10; // Wait
        in = 4'b0100; // Set to 4
        #10; // Wait
        in = 4'b0101; // Set to 5
        #10; // Wait
        in = 4'b0110; // Set to 6
        #10; // Wait
        in = 4'b0111; // Set to 7
        #10; // Wait
        in = 4'b1000; // Set to 8
        #10; // Wait
        in = 4'b1001; // Set to 9
        #10; // Wait
        in = 4'b1010; // Set to 10
        #10; // Wait
        in = 4'b1011; // Set to 11
        #10; // Wait
        in = 4'b1100; // Set to 12
        #10; // Wait
        in = 4'b1101; // Set to 13
        #10; // Wait
        in = 4'b1110; // Set to 14
        #10; // Wait
        in = 4'b1111; // Set to 15
        #10; // End
		
 	end

endmodule

cod_tb.vcd
$date
	Mon Sep 23 08:28:33 2024
$end
$version
	Icarus Verilog
$end
$timescale
	1ns
$end
$scope module cod_tb $end
$var wire 7 ! y [6:0] $end
$var reg 4 " in [3:0] $end
$scope module uut $end
$var wire 4 # in [3:0] $end
$var reg 7 $ y [6:0] $end
$upscope $end
$upscope $end
$enddefinitions $end
$comment Show the parameter values. $end
$dumpall
$end
#0
$dumpvars
b1111110 $
b0 #
b0 "
b1111110 !
$end
#10
b110000 !
b110000 $
b1 "
b1 #
#20
b101101 !
b101101 $
b10 "
b10 #
#30
b1111001 !
b1111001 $
b11 "
b11 #
#40
b110011 !
b110011 $
b100 "
b100 #
#50
b1011011 !
b1011011 $
b101 "
b101 #
#60
b1011111 !
b1011111 $
b110 "
b110 #
#70
b1110000 !
b1110000 $
b111 "
b111 #
#80
b1111111 !
b1111111 $
b1000 "
b1000 #
#90
b1111011 !
b1111011 $
b1001 "
b1001 #
#100
b1110111 !
b1110111 $
b1010 "
b1010 #
#110
b11111 !
b11111 $
b1011 "
b1011 #
#120
b1001110 !
b1001110 $
b1100 "
b1100 #
#130
b111101 !
b111101 $
b1101 "
b1101 #
#140
b1001111 !
b1001111 $
b1110 "
b1110 #
#150
b1000111 !
b1000111 $
b1111 "
b1111 #
