decod.v
module decod(in,EN,d);
    input [2:0] in;
    input EN;
    output reg [7:0] d;
    always @ (in or EN) begin
        if(EN == 1'b1) begin
        case(in)
        3'b000: d = 8'b00000001;
        3'b001: d = 8'b00000010;
        3'b010: d = 8'b00000100;
        3'b011: d = 8'b00001000;
        3'b100: d = 8'b00010000;
        3'b101: d = 8'b00100000;
        3'b110: d = 8'b01000000;
        3'b111: d = 8'b10000000;
        endcase
        end
        else d = 8'b00000000;
    end
endmodule

decod_tb.v
`timescale 1ns/1ns
`include "decod.v"

module decod_tb;
	reg [2:0] in;
    reg EN;
	wire [7:0] d;

	decod uut(in, EN, d);

	initial begin
        $dumpfile("decod_tb.vcd");
        $dumpvars(0, decod_tb);
        EN = 1'b1;
        in =   3'b000; #10;
        in =   3'b001; #10;
        in =   3'b010; #10;
        in =   3'b011; #10;
        in =   3'b100; #10;
        in =   3'b101; #10;
        in =   3'b110; #10;
        in =   3'b111; #10;
        EN = 1'b0;
        in =   3'b000; #10;
        in =   3'b001; #10;
        in =   3'b010; #10;
        in =   3'b011; #10;
        in =   3'b100; #10;
        in =   3'b101; #10;
        in =   3'b110; #10;
        in =   3'b111; #10;

		
 	end

endmodule

decod_tb.vcd
$date
	Mon Sep 23 09:07:22 2024
$end
$version
	Icarus Verilog
$end
$timescale
	1ns
$end
$scope module decod_tb $end
$var wire 8 ! d [7:0] $end
$var reg 1 " EN $end
$var reg 3 # in [2:0] $end
$scope module uut $end
$var wire 1 " EN $end
$var wire 3 $ in [2:0] $end
$var reg 8 % d [7:0] $end
$upscope $end
$upscope $end
$enddefinitions $end
$comment Show the parameter values. $end
$dumpall
$end
#0
$dumpvars
b1 %
b0 $
b0 #
1"
b1 !
$end
#10
b10 !
b10 %
b1 #
b1 $
#20
b100 !
b100 %
b10 #
b10 $
#30
b1000 !
b1000 %
b11 #
b11 $
#40
b10000 !
b10000 %
b100 #
b100 $
#50
b100000 !
b100000 %
b101 #
b101 $
#60
b1000000 !
b1000000 %
b110 #
b110 $
#70
b10000000 !
b10000000 %
b111 #
b111 $
#80
b0 !
b0 %
b0 #
b0 $
0"
#90
b1 #
b1 $
#100
b10 #
b10 $
#110
b11 #
b11 $
#120
b100 #
b100 $
#130
b101 #
b101 $
#140
b110 #
b110 $
#150
b111 #
b111 $
